workspace/src/10counter.v
module counter10(CLK, RES, Q);

input CLK, RES;
output [3:0]Q;

reg  hoge;
wire flag;

reg [3:0]Q;

always @(posedge CLK or negedge RES) 
   if(RES ==1'b0)
       Q = 4'd0;
   else if(Q == 4'd9)
       Q = 4'd0;
   else
       Q = Q + 4'd1;

assign flag = (hoge == 1) ? 1'b1 : 1'b0;

endmodule

workspace/src/10counter_test.v
module counter_test;

reg CLK, RES;
wire [3:0] Q;

counter10 i0(CLK, RES, Q);

always #5  CLK = ~CLK;

initial begin
       CLK = 0;
       RES = 0; #23      RES = 1; #150     $finish;
end

initial begin
       $dumpfile("counter.vcd");
       $dumpvars(0, counter_test);
end

always @(posedge CLK or posedge RES) begin
       if (RES) begin
              i0.hoge <= 0;
       end
       else begin
              i0.hoge <= 1;
       end
end

endmodule

workspace/sim/counter.vcd
$date
	Sat Mar 30 22:13:22 2024
$end
$version
	Icarus Verilog
$end
$timescale
	1s
$end
$scope module counter_test $end
$var wire 4 ! Q [3:0] $end
$var reg 1 " CLK $end
$var reg 1 # RES $end
$scope module i0 $end
$var wire 1 " CLK $end
$var wire 1 # RES $end
$var wire 1 $ flag $end
$var reg 4 % Q [3:0] $end
$var reg 1 & hoge $end
$upscope $end
$upscope $end
$enddefinitions $end
$comment Show the parameter values. $end
$dumpall
$end
#0
$dumpvars
x&
b0 %
x$
0#
0"
b0 !
$end
#5
1$
1&
1"
#10
0"
#15
1"
#20
0"
#23
0$
0&
1#
#25
b1 !
b1 %
1"
#30
0"
#35
b10 !
b10 %
1"
#40
0"
#45
b11 !
b11 %
1"
#50
0"
#55
b100 !
b100 %
1"
#60
0"
#65
b101 !
b101 %
1"
#70
0"
#75
b110 !
b110 %
1"
#80
0"
#85
b111 !
b111 %
1"
#90
0"
#95
b1000 !
b1000 %
1"
#100
0"
#105
b1001 !
b1001 %
1"
#110
0"
#115
b0 !
b0 %
1"
#120
0"
#125
b1 !
b1 %
1"
#130
0"
#135
b10 !
b10 %
1"
#140
0"
#145
b11 !
b11 %
1"
#150
0"
#155
b100 !
b100 %
1"
#160
0"
#165
b101 !
b101 %
1"
